jipdate/__init__.py
jipdate/cfg.py
jipdate/jipcreate.py
jipdate/jipdate.py
jipdate/jipfp.py
jipdate/jipsearch.py
jipdate/jipstatus.py
jipdate/jiralogin.py
jipdate-2.0.3.dist-info/entry_points.txt
jipdate-2.0.3.dist-info/LICENSE
jipdate-2.0.3.dist-info/WHEEL
jipdate-2.0.3.dist-info/METADATA
jipdate-2.0.3.dist-info/RECORD
