Metadata-Version: 2.1
Name: jipdate
Version: 2.0.3
Summary: Command line tool for Jira
Author-email: Joakim Bech <joakim.bech@linaro.org>
Requires-Python: >=3.6
Classifier: License :: OSI Approved :: MIT License
Requires-Dist: jinja2
Requires-Dist: jira
Requires-Dist: PyYAML
Requires-Dist: python-dateutil
Project-URL: Documentation, https://jipdate.readthedocs.io/en/latest/
